{
  "updatedAt": "2026-07-16T00:00:00.000Z",
  "server": {
    "name": "Mangrove AI",
    "memberTotal": 4710,
    "online": 612,
    "humans": 4501,
    "bots": 209,
    "boostTier": 2,
    "boostCount": 14
  },
  "growth": {
    "memberSnapshots": [
      {
        "date": "2026-04-30",
        "members": 4015
      },
      {
        "date": "2026-05-07",
        "members": 4061
      },
      {
        "date": "2026-05-14",
        "members": 4131
      },
      {
        "date": "2026-05-21",
        "members": 4216
      },
      {
        "date": "2026-05-28",
        "members": 4292
      },
      {
        "date": "2026-06-04",
        "members": 4345
      },
      {
        "date": "2026-06-11",
        "members": 4381
      },
      {
        "date": "2026-06-18",
        "members": 4422
      },
      {
        "date": "2026-06-25",
        "members": 4486
      },
      {
        "date": "2026-07-02",
        "members": 4569
      },
      {
        "date": "2026-07-09",
        "members": 4650
      },
      {
        "date": "2026-07-16",
        "members": 4710
      }
    ],
    "joins30d": 430,
    "leaves30d": 168
  },
  "channels": [
    {
      "name": "welcome",
      "type": "text",
      "messages24h": 12,
      "messagesTotal": 1840
    },
    {
      "name": "announcements",
      "type": "announcement",
      "messages24h": 3,
      "messagesTotal": 412
    },
    {
      "name": "general",
      "type": "text",
      "messages24h": 341,
      "messagesTotal": 128940
    },
    {
      "name": "support",
      "type": "text",
      "messages24h": 205,
      "messagesTotal": 74210
    },
    {
      "name": "dev-help",
      "type": "text",
      "messages24h": 176,
      "messagesTotal": 59830
    },
    {
      "name": "showcase",
      "type": "text",
      "messages24h": 64,
      "messagesTotal": 21470
    },
    {
      "name": "feature-requests",
      "type": "forum",
      "messages24h": 41,
      "messagesTotal": 15320
    },
    {
      "name": "off-topic",
      "type": "text",
      "messages24h": 98,
      "messagesTotal": 40115
    },
    {
      "name": "General",
      "type": "voice",
      "messages24h": 0,
      "messagesTotal": 0
    },
    {
      "name": "Office Hours",
      "type": "voice",
      "messages24h": 0,
      "messagesTotal": 0
    }
  ],
  "roles": [
    {
      "name": "Community",
      "memberCount": 4102
    },
    {
      "name": "Beta Tester",
      "memberCount": 486
    },
    {
      "name": "Contributor",
      "memberCount": 152
    },
    {
      "name": "Core Team",
      "memberCount": 11
    },
    {
      "name": "Bots",
      "memberCount": 209
    }
  ],
  "activity": {
    "messagesPerDay": [
      {
        "date": "2026-06-17",
        "count": 847
      },
      {
        "date": "2026-06-18",
        "count": 779
      },
      {
        "date": "2026-06-19",
        "count": 812
      },
      {
        "date": "2026-06-20",
        "count": 368
      },
      {
        "date": "2026-06-21",
        "count": 361
      },
      {
        "date": "2026-06-22",
        "count": 795
      },
      {
        "date": "2026-06-23",
        "count": 753
      },
      {
        "date": "2026-06-24",
        "count": 818
      },
      {
        "date": "2026-06-25",
        "count": 976
      },
      {
        "date": "2026-06-26",
        "count": 947
      },
      {
        "date": "2026-06-27",
        "count": 667
      },
      {
        "date": "2026-06-28",
        "count": 770
      },
      {
        "date": "2026-06-29",
        "count": 983
      },
      {
        "date": "2026-06-30",
        "count": 940
      },
      {
        "date": "2026-07-01",
        "count": 968
      },
      {
        "date": "2026-07-02",
        "count": 809
      },
      {
        "date": "2026-07-03",
        "count": 746
      },
      {
        "date": "2026-07-04",
        "count": 470
      },
      {
        "date": "2026-07-05",
        "count": 360
      },
      {
        "date": "2026-07-06",
        "count": 691
      },
      {
        "date": "2026-07-07",
        "count": 818
      },
      {
        "date": "2026-07-08",
        "count": 787
      },
      {
        "date": "2026-07-09",
        "count": 856
      },
      {
        "date": "2026-07-10",
        "count": 1011
      },
      {
        "date": "2026-07-11",
        "count": 652
      },
      {
        "date": "2026-07-12",
        "count": 678
      },
      {
        "date": "2026-07-13",
        "count": 1084
      },
      {
        "date": "2026-07-14",
        "count": 962
      },
      {
        "date": "2026-07-15",
        "count": 907
      },
      {
        "date": "2026-07-16",
        "count": 930
      }
    ],
    "topChannels": [
      {
        "name": "general",
        "count": 341
      },
      {
        "name": "support",
        "count": 205
      },
      {
        "name": "dev-help",
        "count": 176
      },
      {
        "name": "off-topic",
        "count": 98
      },
      {
        "name": "showcase",
        "count": 64
      },
      {
        "name": "feature-requests",
        "count": 41
      }
    ]
  }
}